{
  "item-states": [
    {
      "folded": false,
      "id": "83ldPIGB5Kq53ZJU6YnSHu"
    },
    {
      "folded": false,
      "id": "14N36NBpFH/JgknJi3N4TT"
    },
    {
      "folded": false,
      "id": "5bg94AcwVElYO/5YmvAgn/"
    },
    {
      "folded": false,
      "id": "48RqshemBKYbYasrg449q/"
    },
    {
      "folded": true,
      "id": "f35pMMhxVJbatuofzlE6aE"
    },
    {
      "folded": false,
      "id": "10KiAltFNDoZniukHGrBPU"
    },
    {
      "folded": false,
      "id": "03k2DgB1BGrJ4Mi5OAAYaW"
    },
    {
      "folded": true,
      "id": "e9AWgtyS1OcbaYuNxfLwfi"
    },
    {
      "folded": false,
      "id": "bf13UdO6ZDPLqPxom9FUM/"
    },
    {
      "folded": false,
      "id": "06gg1KnA5HJbfOA13mgtrA"
    },
    {
      "folded": false,
      "id": "fdKbJzjh5F/KEArpGoJLui"
    },
    {
      "folded": false,
      "id": "72Fcy/YWBPy4F9EwwgiHWO"
    },
    {
      "folded": false,
      "id": "f2+oo9PwxKWp7ZowRGPnTv"
    },
    {
      "folded": false,
      "id": "91oo+Gbn9HPqfM5jYme74z"
    },
    {
      "folded": false,
      "id": "8bozEo1PhAIaBXXGSHtmxR"
    },
    {
      "folded": false,
      "id": "72pYbyrS1NzoZDEPhHgVXl"
    },
    {
      "folded": false,
      "id": "56lFieJWtHbLNkexB9GPsN"
    },
    {
      "folded": true,
      "id": "92+LTSf9FGgoJ8zwUHqJn3"
    }
  ]
}